gym_sailing/__init__.py
gym_sailing/envs/__init__.py
gym_sailing/envs/boat_env.py
gym_sailing/envs/motorboat_env.py
gym_sailing/envs/sailboat_env.py
gym_sailing/physics/__init__.py
gym_sailing/physics/boat.py
gym_sailing/physics/motorboat.py
gym_sailing/physics/sailboat.py
gym_sailing/utils/renderer.py
gym_sailing/utils/utils.py
gym_sailing/utils/assets/laser.png
gym_sailing/utils/assets/sail.png
gym_sailing-0.2.1.dist-info/METADATA
gym_sailing-0.2.1.dist-info/WHEEL
gym_sailing-0.2.1.dist-info/licenses/LICENSE
gym_sailing-0.2.1.dist-info/RECORD
