Metadata-Version: 2.3
Name: gym-sailing
Version: 0.2.1
Summary: A sailing environment for OpenAI Gym / Gymnasium
Project-URL: Homepage, https://github.com/Gabo-Tor/gym-sailing
Project-URL: Issues, https://github.com/Gabo-Tor/gym-sailing/issues
Project-URL: Repository, https://github.com/Gabo-Tor/gym-sailing
Project-URL: Documentation, https://github.com/Gabo-Tor/gym-sailing/blob/main/README.md
Author-email: Gabriel Torre <g-torre@hotmail.com>
License: Copyright 2024 Gabriel Torre
License-File: LICENSE
Keywords: gym,gymnasium,reinforcement learning,sailing
Classifier: License :: OSI Approved :: MIT License
Classifier: Operating System :: OS Independent
Classifier: Programming Language :: Python :: 3
Requires-Python: >=3.8
Requires-Dist: gymnasium>=0.26
Requires-Dist: numpy
Requires-Dist: pygame
